melodia_py/__init__.py
melodia_py/clustering.py
melodia_py/geometryparser.py
melodia_py/main.py
melodia_py/melodia_py.py
melodia_py/data/luthier.dat
melodia_py-0.1.6.dist-info/licenses/LICENSE
melodia_py-0.1.6.dist-info/METADATA
melodia_py-0.1.6.dist-info/WHEEL
melodia_py-0.1.6.dist-info/entry_points.txt
melodia_py-0.1.6.dist-info/top_level.txt
melodia_py-0.1.6.dist-info/RECORD
