Metadata-Version: 2.4
Name: melodia-py
Version: 0.1.6
Summary: Differential Geometry of Proteins Backbones
Home-page: https://github.com/rwmontalvao/Melodia_py
Author: Rinaldo Wander Montalvão, PhD
Author-email: "Rinaldo Wander Montalvão, PhD" <rwmontalvao@gmail.com>
License:                                  Apache License
Project-URL: Homepage, https://github.com/rwmontalvao/Melodia_py
Keywords: protein,differential geometry
Classifier: License :: OSI Approved :: Apache Software License
Classifier: Programming Language :: Python
Classifier: Programming Language :: Python :: 3
Requires-Python: >=3.12
License-File: LICENSE
Requires-Dist: biopython>=1.83
Requires-Dist: pandas>=2.2.2
Requires-Dist: typing-extensions>=4.12
Requires-Dist: seaborn>=0.13.2
Requires-Dist: jupyterlab>=4.2.2
Requires-Dist: tqdm>=4.66.4
Requires-Dist: dill>=0.3.8
Requires-Dist: nglview>=3.1.2
Requires-Dist: pyarrow>=16.1.0
Requires-Dist: scikit-learn>=1.5.0
Requires-Dist: sty>=1.0.0
Requires-Dist: more-itertools>=10.3.0
Dynamic: author
Dynamic: home-page
Dynamic: license-file
